etl/__init__.py
etl/edl.py
etl_tools/__init__.py
etl_tools/api.py
etl_tools/aws.py
etl_tools/execution.py
etl_tools/gcp.py
etl_tools/sql.py
genetl-0.0.80.dist-info/licenses/LICENSE
genetl-0.0.80.dist-info/METADATA
genetl-0.0.80.dist-info/WHEEL
genetl-0.0.80.dist-info/top_level.txt
genetl-0.0.80.dist-info/RECORD
