Metadata-Version: 2.4
Name: GenETL
Version: 0.0.80
Summary: A generic ETL routines module for Python
Author-email: XxZeroGravityxX <XxZeroGravityxX@users.noreply.github.com>
Project-URL: Homepage, https://github.com/XxZeroGravityxX/GenETL
Classifier: Programming Language :: Python :: 3
Classifier: License :: OSI Approved :: MIT License
Classifier: Operating System :: OS Independent
Requires-Python: >=3.9
License-File: LICENSE
Dynamic: license-file
